LICENSE
README.md
files/email.json
maxphisher.py
maxphisher-1.2.2.dist-info/LICENSE
maxphisher-1.2.2.dist-info/METADATA
maxphisher-1.2.2.dist-info/WHEEL
maxphisher-1.2.2.dist-info/entry_points.txt
maxphisher-1.2.2.dist-info/RECORD
