Metadata-Version: 2.1
Name: MaxPhisher
Version: 1.2.2
Summary: A python phishing script for login phishing, image phishing, video phishing and many more
Home-page: https://github.com/KasRoudra/MaxPhisher/
License: MIT
Author: KasRoudra
Author-email: kasroudrakrd@gmail.com
Requires-Python: >=3.9,<4.0
Classifier: License :: OSI Approved :: MIT License
Classifier: Programming Language :: Python :: 3
Classifier: Programming Language :: Python :: 3.9
Classifier: Programming Language :: Python :: 3.10
Classifier: Programming Language :: Python :: 3.11
Classifier: Programming Language :: Python :: 3.12
Requires-Dist: beautifulsoup4 (>=4.12,<5.0)
Requires-Dist: requests (>=2.3.0,<3.0.0)
Requires-Dist: rich (>=13.0.0,<14.0.0)
Project-URL: Repository, https://github.com/KasRoudra/MaxPhisher/
